filesystem_dict-0.1.16.dist-info/licenses/LICENSE.txt
fsdict/__init__.py
fsdict/fsdict.py
fsdict/utils.py
filesystem_dict-0.1.16.dist-info/METADATA
filesystem_dict-0.1.16.dist-info/WHEEL
filesystem_dict-0.1.16.dist-info/top_level.txt
filesystem_dict-0.1.16.dist-info/RECORD
