Metadata-Version: 2.4
Name: filesystem-dict
Version: 0.1.16
Summary: Dictionary like access to the filesystem.
Home-page: https://github.com/MNayer/fsdict
Author: MNayer
Author-email: marie.nayer@web.de
License: 0BSD
Keywords: dictionary,filesystem
License-File: LICENSE.txt
Dynamic: license-file
